[
  {
    "symbol": "ZCN26",
    "weeklyHigh": "444.5",
    "weeklyLow": "421"
  },
  {
    "symbol": "ZCZ26",
    "weeklyHigh": "465.75",
    "weeklyLow": "440.5"
  },
  {
    "symbol": "KEN26",
    "weeklyHigh": "644",
    "weeklyLow": "620.75"
  },
  {
    "symbol": "ZRN26",
    "weeklyHigh": "13.5",
    "weeklyLow": "12.8"
  },
  {
    "symbol": "ZMN26",
    "weeklyHigh": "319.5",
    "weeklyLow": "307"
  },
  {
    "symbol": "ZLN26",
    "weeklyHigh": "71.43",
    "weeklyLow": "66.87"
  },
  {
    "symbol": "ZSN26",
    "weeklyHigh": "1207.75",
    "weeklyLow": "1126.25"
  },
  {
    "symbol": "ZSX26",
    "weeklyHigh": "1204",
    "weeklyLow": "1146.25"
  },
  {
    "symbol": "ZWN26",
    "weeklyHigh": "613.75",
    "weeklyLow": "590.25"
  }
]